logging_prometheus/__init__.py
logging_prometheus-0.1.0.dist-info/LICENSE
logging_prometheus-0.1.0.dist-info/METADATA
logging_prometheus-0.1.0.dist-info/WHEEL
logging_prometheus-0.1.0.dist-info/top_level.txt
logging_prometheus-0.1.0.dist-info/RECORD
