Metadata-Version: 2.1
Name: logging-prometheus
Version: 0.1.0
Summary: Exports logging metrics for Prometheus.io.
Home-page: http://github.com/korfuri/python-logging-prometheus
Author: Uriel Corfa
Author-email: uriel@corfa.fr
License: Apache
Keywords: python logging monitoring prometheus
Platform: UNKNOWN
Classifier: Development Status :: 5 - Production/Stable
Classifier: Intended Audience :: Developers
Classifier: Intended Audience :: Information Technology
Classifier: Intended Audience :: System Administrators
Classifier: Topic :: System :: Monitoring
Classifier: Programming Language :: Python :: 2
Classifier: Programming Language :: Python :: 2.7
Classifier: Programming Language :: Python :: 3
Classifier: Programming Language :: Python :: 3.5
Classifier: Programming Language :: Python :: 3.6
Classifier: Programming Language :: Python :: 3.7
Classifier: License :: OSI Approved :: Apache Software License
Requires-Dist: prometheus-client (>=0.0.8)
